zetuptools/__init__.py
zetuptools/__main__.py
zetuptools/api.py
zetuptools-4.0.1.dist-info/entry_points.txt
zetuptools-4.0.1.dist-info/LICENSE
zetuptools-4.0.1.dist-info/WHEEL
zetuptools-4.0.1.dist-info/METADATA
zetuptools-4.0.1.dist-info/RECORD
