Metadata-Version: 2.1
Name: zetuptools
Version: 4.0.1
Summary: Useful for doing post-install/uninstall things
Home-page: https://github.com/zmarffy/zetuptools
License: MIT
Author: Zeke Marffy
Author-email: zmarffy@me.com
Requires-Python: >=3.8,<4.0
Classifier: License :: OSI Approved :: MIT License
Classifier: Programming Language :: Python :: 3
Classifier: Programming Language :: Python :: 3.10
Classifier: Programming Language :: Python :: 3.8
Classifier: Programming Language :: Python :: 3.9
Requires-Dist: docker (>=5.0.3,<6.0.0)
Requires-Dist: dunamai (>=1.8.0,<2.0.0)
Requires-Dist: zmtools (>=2.0.0)
Project-URL: Repository, https://github.com/zmarffy/zetuptools
